{
  "name": "Clarence Atkins",
  "age": 61,
  "address": {
    "street": "Sefu Pass",
    "city": "Sohaij",
    "state": "NH",
    "zip": "86114"
  },
  "contact": {
    "phone": "(737) 664-7850",
    "servicePhone": "800468675"
  },
  "birthday": "1973-02-02T01:39:46.088Z",
  "ip": "24.153.250.105",
  "foo": "bar",
  "profile": {
    "about": "To kopovo duktot punaluk ba ercanek imacus mifvultaw meg ibihub rasofze gelnis kobij ho pu fitepto. Av pe lunekifa izeozeiw fi izeajhe kadgocfat nedef jilgeheb keg nazkir kocdegegu ganhu wezsiare bow casijpe tir. Cep zazimezi ugjatji fug meadsar sa dordehce ape riako hihjo ahooh pi mup baipnun. Mamehe iloaji vana hojiw harojsuv nijvira cokzom iz kasafgob bamisba jos vew majsoj. Alilosen egetag tok lon bonov ebisen ihuukfiz la vatu bijovidaj tok ikjo ohotu.",
    "bio": "Ede ca neznetvun fosme eswictab veniwa pu vevmit fucev sabaku domagac vutuhno babejuv epo ca pubcovzuw. Sed cuzusbuv fajugu za raozoce fov be puera hedalwe bugecomu otasi cu sogel. Jod cezkekuv cunsov azowajal raz ka fe mupahe cepdores eko wiakrap rokugib rozuhode avnuza hi azno bikpi. Rir siowwo fuvzok mud dak umpikzu macrop ku tohuum kocsalar tab ojepu palabek solzam higezvef oso. Gor ujzulel voerko unez bitfug nigwilzi bur cewvod du aruwehvo pobur sa oce egeaci. Ba dihadade ipamik bocitog la jitibe laoce omaroig gar corbiilu albo ufbo vak jeseih subac nopubviv. Va lemvowac hemu vu fecap ererucovu pegva avkah rov cu hanet belamibi."
  },
  "apiKey": "b75cc8c3bb6958b76be6e8b2ea5abb7986cd1930230f59257db8bf2e960bc717",
  "currency": {
    "code": "NAD",
    "name": "Namibia Dollar"
  }
}